livetranscriber.py
livetranscriber-0.3.13.dist-info/licenses/LICENSE
livetranscriber-0.3.13.dist-info/METADATA
livetranscriber-0.3.13.dist-info/WHEEL
livetranscriber-0.3.13.dist-info/entry_points.txt
livetranscriber-0.3.13.dist-info/top_level.txt
livetranscriber-0.3.13.dist-info/RECORD
