Metadata-Version: 2.4
Name: livetranscriber
Version: 0.3.13
Summary: Real-time microphone transcription with Deepgram using Python.
Author-email: Avi <sixfold.fellas4a@icloud.com>
License-Expression: MIT
Project-URL: Homepage, https://aviralgarg.com
Project-URL: Source, https://github.com/gaviral/livetranscriber
Project-URL: Bug Tracker, https://github.com/gaviral/livetranscriber/issues
Keywords: transcription,speech-to-text,deepgram,real-time,python,audio
Classifier: Programming Language :: Python :: 3
Classifier: Operating System :: OS Independent
Requires-Python: ==3.11.*
License-File: LICENSE
Requires-Dist: deepgram-sdk<5,>=4
Requires-Dist: numpy>=1.24
Requires-Dist: sounddevice>=0.4
Dynamic: license-file
